#ifndef OPCODE_HPP
#define OPCODE_HPP

#define JAVA_OPCODE_NOP 0X00
#define JAVA_OPCODE_ACONST_NULL 0X01
#define JAVA_OPCODE_ICONST_M1 0X02
#define JAVA_OPCODE_ICONST_0 0X03
#define JAVA_OPCODE_ICONST_1 0X04
#define JAVA_OPCODE_ICONST_2 0X05
#define JAVA_OPCODE_ICONST_3 0X06
#define JAVA_OPCODE_ICONST_4 0X07
#define JAVA_OPCODE_ICONST_5 0X08
#define JAVA_OPCODE_LCONST_0 0X09
#define JAVA_OPCODE_LCONST_1 0X0A
#define JAVA_OPCODE_FCONST_0 0X0B
#define JAVA_OPCODE_FCONST_1 0X0C
#define JAVA_OPCODE_FCONST_2 0X0D
#define JAVA_OPCODE_DCONST_0 0X0E
#define JAVA_OPCODE_DCONST_1 0X0F
#define JAVA_OPCODE_BIPUSH 0X10
#define JAVA_OPCODE_SIPUSH 0X11
#define JAVA_OPCODE_LDC 0X12
#define JAVA_OPCODE_LDC_W 0X13
#define JAVA_OPCODE_LDC2_W 0X14
#define JAVA_OPCODE_ILOAD 0X15
#define JAVA_OPCODE_LLOAD 0X16
#define JAVA_OPCODE_FLOAD 0X17
#define JAVA_OPCODE_DLOAD 0X18
#define JAVA_OPCODE_ALOAD 0X19
#define JAVA_OPCODE_ILOAD_0 0X1A
#define JAVA_OPCODE_ILOAD_1 0X1B
#define JAVA_OPCODE_ILOAD_2 0X1C
#define JAVA_OPCODE_ILOAD_3 0X1D
#define JAVA_OPCODE_LLOAD_0 0X1E
#define JAVA_OPCODE_LLOAD_1 0X1F
#define JAVA_OPCODE_LLOAD_2 0X20
#define JAVA_OPCODE_LLOAD_3 0X21
#define JAVA_OPCODE_FLOAD_0 0X22
#define JAVA_OPCODE_FLOAD_1 0X23
#define JAVA_OPCODE_FLOAD_2 0X24
#define JAVA_OPCODE_FLOAD_3 0X25
#define JAVA_OPCODE_DLOAD_0 0X26
#define JAVA_OPCODE_DLOAD_1 0X27
#define JAVA_OPCODE_DLOAD_2 0X28
#define JAVA_OPCODE_DLOAD_3 0X29
#define JAVA_OPCODE_ALOAD_0 0X2A
#define JAVA_OPCODE_ALOAD_1 0X2B
#define JAVA_OPCODE_ALOAD_2 0X2C
#define JAVA_OPCODE_ALOAD_3 0X2D
#define JAVA_OPCODE_IALOAD 0X2E
#define JAVA_OPCODE_LALOAD 0X2F
#define JAVA_OPCODE_FALOAD 0X30
#define JAVA_OPCODE_DALOAD 0X31
#define JAVA_OPCODE_AALOAD 0X32
#define JAVA_OPCODE_BALOAD 0X33
#define JAVA_OPCODE_CALOAD 0X34
#define JAVA_OPCODE_SALOAD 0X35
#define JAVA_OPCODE_ISTORE 0X36
#define JAVA_OPCODE_LSTORE 0X37
#define JAVA_OPCODE_FSTORE 0X38
#define JAVA_OPCODE_DSTORE 0X39
#define JAVA_OPCODE_ASTORE 0X3A
#define JAVA_OPCODE_ISTORE_0 0X3B
#define JAVA_OPCODE_ISTORE_1 0X3C
#define JAVA_OPCODE_ISTORE_2 0X3D
#define JAVA_OPCODE_ISTORE_3 0X3E
#define JAVA_OPCODE_LSTORE_0 0X3F
#define JAVA_OPCODE_LSTORE_1 0X40
#define JAVA_OPCODE_LSTORE_2 0X41
#define JAVA_OPCODE_LSTORE_3 0X42
#define JAVA_OPCODE_FSTORE_0 0X43
#define JAVA_OPCODE_FSTORE_1 0X44
#define JAVA_OPCODE_FSTORE_2 0X45
#define JAVA_OPCODE_FSTORE_3 0X46
#define JAVA_OPCODE_DSTORE_0 0X47
#define JAVA_OPCODE_DSTORE_1 0X48
#define JAVA_OPCODE_DSTORE_2 0X49
#define JAVA_OPCODE_DSTORE_3 0X4A
#define JAVA_OPCODE_ASTORE_0 0X4B
#define JAVA_OPCODE_ASTORE_1 0X4C
#define JAVA_OPCODE_ASTORE_2 0X4D
#define JAVA_OPCODE_ASTORE_3 0X4E
#define JAVA_OPCODE_IASTORE 0X4F
#define JAVA_OPCODE_LASTORE 0X50
#define JAVA_OPCODE_FASTORE 0X51
#define JAVA_OPCODE_DASTORE 0X52
#define JAVA_OPCODE_AASTORE 0X53
#define JAVA_OPCODE_BASTORE 0X54
#define JAVA_OPCODE_CASTORE 0X55
#define JAVA_OPCODE_SASTORE 0X56
#define JAVA_OPCODDE_POP 0X57
#define JAVA_OPCODDE_POP2 0X58
#define JAVA_OPCODDE_DUP 0X59
#define JAVA_OPCODDE_DUP_X1 0X5A
#define JAVA_OPCODDE_DUP_X2 0X5B
#define JAVA_OPCODDE_DUP2 0X5C
#define JAVA_OPCODDE_DUP2_X1 0X5D
#define JAVA_OPCODDE_DUP2_X2 0X5E
#define JAVA_OPCODDE_SWAP 0X5F
#define JAVA_OPCODDE_IADD 0X60
#define JAVA_OPCODDE_LADD 0X61
#define JAVA_OPCODDE_FADD 0X62
#define JAVA_OPCODDE_DADD 0X63
#define JAVA_OPCODDE_ISUB 0X64
#define JAVA_OPCODDE_LSUB 0X65
#define JAVA_OPCODDE_FSUB 0X66
#define JAVA_OPCODDE_DSUB 0X67
#define JAVA_OPCODDE_IMUL 0X68
#define JAVA_OPCODDE_LMUL 0X69
#define JAVA_OPCODDE_FMUL 0X6A
#define JAVA_OPCODDE_DMUL 0X6B
#define JAVA_OPCODDE_IDIV 0X6C
#define JAVA_OPCODDE_LDIV 0X6D
#define JAVA_OPCODDE_FDIV 0X6E
#define JAVA_OPCODDE_DDIV 0X6F
#define JAVA_OPCODDE_IREM 0X70
#define JAVA_OPCODDE_LREM 0X71
#define JAVA_OPCODDE_FREM 0X72
#define JAVA_OPCODDE_DREM 0X73
#define JAVA_OPCODDE_INEG 0X74
#define JAVA_OPCODDE_LNEG 0X75
#define JAVA_OPCODDE_FNEG 0X76
#define JAVA_OPCODDE_DNEG 0X77
#define JAVA_OPCODDE_ISHL 0X78
#define JAVA_OPCODDE_LSHL 0X79
#define JAVA_OPCODDE_ISHR 0X7A
#define JAVA_OPCODDE_LSHR 0X7B
#define JAVA_OPCODDE_IUSHR 0X7C
#define JAVA_OPCODDE_LUSHR 0X7D
#define JAVA_OPCODDE_IAND 0X7E
#define JAVA_OPCODDE_LAND 0X7F
#define JAVA_OPCODDE_IOR 0X80
#define JAVA_OPCODDE_LOR 0X81
#define JAVA_OPCODDE_IXOR 0X82
#define JAVA_OPCODDE_LXOR 0X83
#define JAVA_OPCODDE_IINC 0X84
#define JAVA_OPCODDE_I2L 0X85
#define JAVA_OPCODDE_I2F 0X86
#define JAVA_OPCODDE_I2D 0X87
#define JAVA_OPCODDE_L2I 0X88
#define JAVA_OPCODDE_L2F 0X89
#define JAVA_OPCODDE_L2D 0X8A
#define JAVA_OPCODDE_F2I 0X8B
#define JAVA_OPCODDE_F2L 0X8C
#define JAVA_OPCODDE_F2D 0X8D
#define JAVA_OPCODDE_D2I 0X8E
#define JAVA_OPCODDE_D2L 0X8F
#define JAVA_OPCODDE_D2F 0X90
#define JAVA_OPCODDE_I2B 0X91
#define JAVA_OPCODDE_I2C 0X92
#define JAVA_OPCODDE_I2S 0X93
#define JAVA_OPCODDE_LCMP 0X94
#define JAVA_OPCODDE_FCMPL 0X95
#define JAVA_OPCODDE_FCMPG 0X96
#define JAVA_OPCODDE_DCMPL 0X97
#define JAVA_OPCODDE_DCMPG 0X98
#define JAVA_OPCODDE_IFEQ 0X99
#define JAVA_OPCODDE_IFNE 0X9A
#define JAVA_OPCODDE_IFLT 0X9B
#define JAVA_OPCODDE_IFGE 0X9C
#define JAVA_OPCODDE_IFGT 0X9D
#define JAVA_OPCODDE_IFLE 0X9E
#define JAVA_OPCODDE_IF_ICMPEQ 0X9F
#define JAVA_OPCODDE_IF_ICMPNE 0XA0
#define JAVA_OPCODDE_IF_ICMPLT 0XA1
#define JAVA_OPCODDE_IF_ICMPGE 0XA2
#define JAVA_OPCODDE_IF_ICMPGT 0XA3
#define JAVA_OPCODDE_IF_ICMPLE 0XA4
#define JAVA_OPCODDE_IF_ACMPEQ 0XA5
#define JAVA_OPCODDE_IF_ACMPNE 0XA6
#define JAVA_OPCODDE_GOTO 0XA7
#define JAVA_OPCODDE_JSR 0XA8
#define JAVA_OPCODDE_RET 0XA9
#define JAVA_OPCODDE_TABLESWITCH 0XAA
#define JAVA_OPCODDE_LOOKUPSWITCH 0XAB
#define JAVA_OPCODDE_IRETURN 0XAC
#define JAVA_OPCODDE_LRETURN 0XAD
#define JAVA_OPCODDE_FRETURN 0XAE
#define JAVA_OPCODDE_DRETURN 0XAF
#define JAVA_OPCODDE_ARETURN 0XB0
#define JAVA_OPCODDE_RETURN 0XB1
#define JAVA_OPCODDE_GETSTATIC 0XB2
#define JAVA_OPCODDE_PUTSTATIC 0XB3
#define JAVA_OPCODDE_GETFIELD 0XB4
#define JAVA_OPCODDE_PUTFIELD 0XB5
#define JAVA_OPCODDE_INVOKEVIRTUAL 0XB6
#define JAVA_OPCODDE_INVOKESPECIAL 0XB7
#define JAVA_OPCODDE_INVOKESTATIC 0XB8
#define JAVA_OPCODDE_INVOKEINTERFACE 0XB9
#define JAVA_OPCODDE_INVOKEDYNAMIC 0XBA
#define JAVA_OPCODDE_NEW 0XBB
#define JAVA_OPCODDE_NEWARRAY 0XBC
#define JAVA_OPCODDE_ANEWARRAY 0XBD
#define JAVA_OPCODDE_ARRAYLENGTH 0XBE
#define JAVA_OPCODDE_ATHROW 0XBF
#define JAVA_OPCODDE_CHECKCAST 0XC0
#define JAVA_OPCODDE_INSTANCEOF 0XC1
#define JAVA_OPCODDE_MONITORENTER 0XC2
#define JAVA_OPCODDE_MONITOREXIT 0XC3
#define JAVA_OPCODDE_WIDE 0XC4
#define JAVA_OPCODDE_MULTIANEWARRAY 0XC5
#define JAVA_OPCODDE_IFNULL 0XC6
#define JAVA_OPCODDE_IFNONNULL 0XC7
#define JAVA_OPCODDE_GOTO_W 0XC8
#define JAVA_OPCODDE_JSR_W 0XC9
#define JAVA_OPCODDE_BREAKPOINT 0XCA
#define JAVA_OPCODDE_IMPDEP1 0XFE
#define JAVA_OPCODDE_IMPDEP2 0XFF

#include<map>
#include<string>
#include<stdint.h>

using namespace std;

class OpCode
{
	private:
		static OpCode *ref;
		map<uint8_t, string> mapa;
		void InicializarMapa();
		OpCode(void);
	public:
		static OpCode* GetReferencia(void);
		string GetMinemonico(uint8_t bytecode);
};

#endif
